tachyon/__init__.py
tachyon/__main__.py
tachyon/tachyon.py
tachyon/tools.py
tachydownloader-0.0.9.dist-info/METADATA
tachydownloader-0.0.9.dist-info/WHEEL
tachydownloader-0.0.9.dist-info/entry_points.txt
tachydownloader-0.0.9.dist-info/top_level.txt
tachydownloader-0.0.9.dist-info/RECORD
