Metadata-Version: 2.1
Name: tachydownloader
Version: 0.0.9
Summary: Tachyon — The faster than light media downloader
Home-page: https://github.com/aaaakshat/tachyon
Author: Akshat Bisht
Author-email: akshatbisht002@gmail.com
License: UNKNOWN
Platform: UNKNOWN
Classifier: Programming Language :: Python
Classifier: Programming Language :: Python :: 3 :: Only
Classifier: License :: OSI Approved :: MIT License
Classifier: Operating System :: MacOS
Classifier: Topic :: Multimedia :: Video
Classifier: Topic :: Multimedia :: Sound/Audio
Classifier: Topic :: Internet :: WWW/HTTP
Classifier: Topic :: Utilities
